{
  "updated_at": "2026-06-27T21:57:48Z",
  "oepnv_aktuell": {
    "avg_delay_min": 13.32,
    "median_delay_min": 0.0,
    "n_departures": 220,
    "pct_on_time": 78.6,
    "pct_over_3min": 15.9,
    "pct_over_5min": 15.0,
    "stadtbahn": {
      "avg_delay_min": 16.32,
      "median_delay_min": 0.0,
      "n": 40,
      "pct_on_time": 77.5,
      "pct_over_3min": 15.0
    },
    "kaserne": {
      "avg_delay_min": 13.15,
      "median_delay_min": 0.0,
      "n": 40,
      "pct_on_time": 67.5,
      "pct_over_3min": 22.5
    },
    "b56": {
      "avg_delay_min": 24.77,
      "median_delay_min": 0.0,
      "n": 40,
      "pct_on_time": 75.0,
      "pct_over_3min": 25.0
    },
    "beuel": {
      "avg_delay_min": 0.72,
      "median_delay_min": 0.0,
      "n": 40,
      "pct_on_time": 90.0,
      "pct_over_3min": 7.5
    }
  },
  "miv": {
    "12": {
      "name": "A59 → Kennedybrücke",
      "current_min": 6.5,
      "avg_min": 6.8,
      "delta_min": -0.3,
      "status": "fast"
    },
    "149": {
      "name": "Kennedybrücke → A59",
      "current_min": 5.5,
      "avg_min": 5.7,
      "delta_min": -0.2,
      "status": "fast"
    },
    "14": {
      "name": "Kölnstr. → Bertha",
      "current_min": 5.8,
      "avg_min": 6.9,
      "delta_min": -1.1,
      "status": "fast"
    }
  },
  "oepnv_7tage": {
    "available": true,
    "days_collected": 8,
    "innenstadt": {
      "avg_delay_min": 4.04,
      "pct_on_time": 84.6,
      "n": 6900
    },
    "Kasernenstr_bleibt": {
      "avg_delay_min": 3.72,
      "pct_on_time": 82.7,
      "n": 4590
    },
    "Adenauerallee_ref": {
      "avg_delay_min": 1.91,
      "pct_on_time": 89.5,
      "n": 4590
    },
    "B56_entfaellt": {
      "avg_delay_min": 3.34,
      "pct_on_time": 88.7,
      "n": 4590
    },
    "stadtbahn": {
      "avg_delay_min": 4.5,
      "pct_on_time": 84.0,
      "n": 4560
    },
    "beuel": {
      "avg_delay_min": 1.2,
      "pct_on_time": 88.4,
      "n": 4560
    }
  },
  "miv_7tage": {
    "available": true,
    "days_collected": 7,
    "avg_current_min": 8.7,
    "avg_delta_min": 1.88,
    "n": 42
  }
}